README.rst
setup.cfg
setup.py
v2/MANIFEST.in
v2/__init__.py
v2/__main__.py
v2.egg-info/PKG-INFO
v2.egg-info/SOURCES.txt
v2.egg-info/dependency_links.txt
v2.egg-info/entry_points.txt
v2.egg-info/requires.txt
v2.egg-info/top_level.txt