Metadata-Version: 1.1
Name: v2
Version: 1.0.6
Summary: Intelligent auto-versioning.
Home-page: https://github.com/solidsnack/v2
Author: Jason Dusek
Author-email: jason.dusek@gmail.com
License: UNKNOWN
Platform: UNKNOWN
Classifier: Environment :: Console
Classifier: Intended Audience :: Developers
Classifier: License :: OSI Approved :: MIT License
Classifier: Operating System :: Unix
Classifier: Operating System :: POSIX
Classifier: Programming Language :: Python
Classifier: Programming Language :: Python :: 2.7
Classifier: Programming Language :: Python :: 3.5
Classifier: Topic :: Software Development
Classifier: Development Status :: 4 - Beta
